{
  "version": "1",
  "table": {
    "version": "2",
    "table_id": "CJERV6ZM",
    "columns": [
      {
        "index": 0,
        "name": "col0",
        "values": [
          "Formhr Police Station",
          "Former Charles Street Police Staion",
          "Police Statio",
          "Old Police Staton",
          "Police Staion",
          "Ole Police Station",
          "Snow Hill Solce Station",
          "Police Stction",
          "Qartel da Luz",
          "Police Sttion",
          "Qolice Station",
          "Police Stauion",
          "Old PoliceStbtion",
          "Dockyard#Police Station",
          "Olf Police Station",
          "Greater Mbnchester Police Museum and Archives",
          "UheOld Police Station",
          "Plice Station And Magistrates' Court",
          "ld Police Station",
          "The Old Police Stawion"
        ]
      },
      {
        "index": 1,
        "name": "col1",
        "values": [
          "Grade II listed building",
          "Grade II listed building",
          "Grade II listed building",
          "Grade II listed building",
          "Grade II listed building",
          "Grade II listed building",
          "Grade II listed building",
          "Grade II listed building",
          "CONDEPHAAT Good Class",
          "Grade II listed building",
          "Grade II listed building",
          "Grade II listed building",
          "Grade II listed building",
          "Grade II listed building",
          "Grade II listed building",
          "Grade II listed building",
          "Grade II listed building",
          "Grade II listed building",
          "Grade II listed building",
          "Grade II listed building"
        ]
      },
      {
        "index": 2,
        "name": "col2",
        "values": [
          "Walsall",
          "Leicester",
          "Leicester",
          "Lyme Regis",
          "Derby",
          "Wotton-under-Edge",
          "City of London",
          "Northumberland",
          "S\u00e3o Paulo",
          "Aiskew and Leeming Bar",
          "Cambridge",
          "Staffordshire",
          "Staffordshire",
          "Dorset",
          "City of Bristol",
          "Manchester",
          "Bromyard and Winslow",
          "Brampton",
          "Kirton in Lindsey",
          "Norton St Philip"
        ]
      }
    ]
  },
  "context": {
    "page_title": null,
    "page_url": null,
    "page_qnode": null
  },
  "links": [
    [
      [
        {
          "start": 0,
          "end": 21,
          "url": "http://www.wikidata.org/entity/Q26606169",
          "qnode_id": "Q26606169"
        }
      ],
      [
        {
          "start": 0,
          "end": 24,
          "url": "http://www.wikidata.org/entity/Q15700834",
          "qnode_id": "Q15700834"
        }
      ],
      [
        {
          "start": 0,
          "end": 7,
          "url": "http://www.wikidata.org/entity/Q178356",
          "qnode_id": "Q178356"
        }
      ]
    ],
    [
      [
        {
          "start": 0,
          "end": 35,
          "url": "http://www.wikidata.org/entity/Q26667346",
          "qnode_id": "Q26667346"
        }
      ],
      [
        {
          "start": 0,
          "end": 24,
          "url": "http://www.wikidata.org/entity/Q15700834",
          "qnode_id": "Q15700834"
        }
      ],
      [
        {
          "start": 0,
          "end": 9,
          "url": "http://www.wikidata.org/entity/Q83065",
          "qnode_id": "Q83065"
        }
      ]
    ],
    [
      [
        {
          "start": 0,
          "end": 13,
          "url": "http://www.wikidata.org/entity/Q26554161",
          "qnode_id": "Q26554161"
        }
      ],
      [
        {
          "start": 0,
          "end": 24,
          "url": "http://www.wikidata.org/entity/Q15700834",
          "qnode_id": "Q15700834"
        }
      ],
      [
        {
          "start": 0,
          "end": 9,
          "url": "http://www.wikidata.org/entity/Q83065",
          "qnode_id": "Q83065"
        }
      ]
    ],
    [
      [
        {
          "start": 0,
          "end": 17,
          "url": "http://www.wikidata.org/entity/Q26568247",
          "qnode_id": "Q26568247"
        }
      ],
      [
        {
          "start": 0,
          "end": 24,
          "url": "http://www.wikidata.org/entity/Q15700834",
          "qnode_id": "Q15700834"
        }
      ],
      [
        {
          "start": 0,
          "end": 10,
          "url": "http://www.wikidata.org/entity/Q82490",
          "qnode_id": "Q82490"
        }
      ]
    ],
    [
      [
        {
          "start": 0,
          "end": 13,
          "url": "http://www.wikidata.org/entity/Q26522996",
          "qnode_id": "Q26522996"
        }
      ],
      [
        {
          "start": 0,
          "end": 24,
          "url": "http://www.wikidata.org/entity/Q15700834",
          "qnode_id": "Q15700834"
        }
      ],
      [
        {
          "start": 0,
          "end": 5,
          "url": "http://www.wikidata.org/entity/Q43475",
          "qnode_id": "Q43475"
        }
      ]
    ],
    [
      [
        {
          "start": 0,
          "end": 18,
          "url": "http://www.wikidata.org/entity/Q26625609",
          "qnode_id": "Q26625609"
        }
      ],
      [
        {
          "start": 0,
          "end": 24,
          "url": "http://www.wikidata.org/entity/Q15700834",
          "qnode_id": "Q15700834"
        }
      ],
      [
        {
          "start": 0,
          "end": 17,
          "url": "http://www.wikidata.org/entity/Q29471",
          "qnode_id": "Q29471"
        }
      ]
    ],
    [
      [
        {
          "start": 0,
          "end": 23,
          "url": "http://www.wikidata.org/entity/Q27086060",
          "qnode_id": "Q27086060"
        }
      ],
      [
        {
          "start": 0,
          "end": 24,
          "url": "http://www.wikidata.org/entity/Q15700834",
          "qnode_id": "Q15700834"
        }
      ],
      [
        {
          "start": 0,
          "end": 14,
          "url": "http://www.wikidata.org/entity/Q23311",
          "qnode_id": "Q23311"
        }
      ]
    ],
    [
      [
        {
          "start": 0,
          "end": 14,
          "url": "http://www.wikidata.org/entity/Q26652581",
          "qnode_id": "Q26652581"
        }
      ],
      [
        {
          "start": 0,
          "end": 24,
          "url": "http://www.wikidata.org/entity/Q15700834",
          "qnode_id": "Q15700834"
        }
      ],
      [
        {
          "start": 0,
          "end": 14,
          "url": "http://www.wikidata.org/entity/Q23079",
          "qnode_id": "Q23079"
        }
      ]
    ],
    [
      [
        {
          "start": 0,
          "end": 13,
          "url": "http://www.wikidata.org/entity/Q28657496",
          "qnode_id": "Q28657496"
        }
      ],
      [
        {
          "start": 0,
          "end": 21,
          "url": "http://www.wikidata.org/entity/Q45824471",
          "qnode_id": "Q45824471"
        }
      ],
      [
        {
          "start": 0,
          "end": 9,
          "url": "http://www.wikidata.org/entity/Q174",
          "qnode_id": "Q174"
        }
      ]
    ],
    [
      [
        {
          "start": 0,
          "end": 13,
          "url": "http://www.wikidata.org/entity/Q26443703",
          "qnode_id": "Q26443703"
        }
      ],
      [
        {
          "start": 0,
          "end": 24,
          "url": "http://www.wikidata.org/entity/Q15700834",
          "qnode_id": "Q15700834"
        }
      ],
      [
        {
          "start": 0,
          "end": 22,
          "url": "http://www.wikidata.org/entity/Q65040702",
          "qnode_id": "Q65040702"
        }
      ]
    ],
    [
      [
        {
          "start": 0,
          "end": 14,
          "url": "http://www.wikidata.org/entity/Q26321380",
          "qnode_id": "Q26321380"
        }
      ],
      [
        {
          "start": 0,
          "end": 24,
          "url": "http://www.wikidata.org/entity/Q15700834",
          "qnode_id": "Q15700834"
        }
      ],
      [
        {
          "start": 0,
          "end": 9,
          "url": "http://www.wikidata.org/entity/Q21713103",
          "qnode_id": "Q21713103"
        }
      ]
    ],
    [
      [
        {
          "start": 0,
          "end": 14,
          "url": "http://www.wikidata.org/entity/Q26290558",
          "qnode_id": "Q26290558"
        }
      ],
      [
        {
          "start": 0,
          "end": 24,
          "url": "http://www.wikidata.org/entity/Q15700834",
          "qnode_id": "Q15700834"
        }
      ],
      [
        {
          "start": 0,
          "end": 13,
          "url": "http://www.wikidata.org/entity/Q21694786",
          "qnode_id": "Q21694786"
        }
      ]
    ],
    [
      [
        {
          "start": 0,
          "end": 17,
          "url": "http://www.wikidata.org/entity/Q26289642",
          "qnode_id": "Q26289642"
        }
      ],
      [
        {
          "start": 0,
          "end": 24,
          "url": "http://www.wikidata.org/entity/Q15700834",
          "qnode_id": "Q15700834"
        }
      ],
      [
        {
          "start": 0,
          "end": 13,
          "url": "http://www.wikidata.org/entity/Q21694786",
          "qnode_id": "Q21694786"
        }
      ]
    ],
    [
      [
        {
          "start": 0,
          "end": 23,
          "url": "http://www.wikidata.org/entity/Q26498636",
          "qnode_id": "Q26498636"
        }
      ],
      [
        {
          "start": 0,
          "end": 24,
          "url": "http://www.wikidata.org/entity/Q15700834",
          "qnode_id": "Q15700834"
        }
      ],
      [
        {
          "start": 0,
          "end": 6,
          "url": "http://www.wikidata.org/entity/Q21694711",
          "qnode_id": "Q21694711"
        }
      ]
    ],
    [
      [
        {
          "start": 0,
          "end": 18,
          "url": "http://www.wikidata.org/entity/Q26499555",
          "qnode_id": "Q26499555"
        }
      ],
      [
        {
          "start": 0,
          "end": 24,
          "url": "http://www.wikidata.org/entity/Q15700834",
          "qnode_id": "Q15700834"
        }
      ],
      [
        {
          "start": 0,
          "end": 15,
          "url": "http://www.wikidata.org/entity/Q21693433",
          "qnode_id": "Q21693433"
        }
      ]
    ],
    [
      [
        {
          "start": 0,
          "end": 45,
          "url": "http://www.wikidata.org/entity/Q17361850",
          "qnode_id": "Q17361850"
        }
      ],
      [
        {
          "start": 0,
          "end": 24,
          "url": "http://www.wikidata.org/entity/Q15700834",
          "qnode_id": "Q15700834"
        }
      ],
      [
        {
          "start": 0,
          "end": 10,
          "url": "http://www.wikidata.org/entity/Q21525592",
          "qnode_id": "Q21525592"
        }
      ]
    ],
    [
      [
        {
          "start": 0,
          "end": 21,
          "url": "http://www.wikidata.org/entity/Q26471670",
          "qnode_id": "Q26471670"
        }
      ],
      [
        {
          "start": 0,
          "end": 24,
          "url": "http://www.wikidata.org/entity/Q15700834",
          "qnode_id": "Q15700834"
        }
      ],
      [
        {
          "start": 0,
          "end": 20,
          "url": "http://www.wikidata.org/entity/Q3784412",
          "qnode_id": "Q3784412"
        }
      ]
    ],
    [
      [
        {
          "start": 0,
          "end": 36,
          "url": "http://www.wikidata.org/entity/Q26380057",
          "qnode_id": "Q26380057"
        }
      ],
      [
        {
          "start": 0,
          "end": 24,
          "url": "http://www.wikidata.org/entity/Q15700834",
          "qnode_id": "Q15700834"
        }
      ],
      [
        {
          "start": 0,
          "end": 8,
          "url": "http://www.wikidata.org/entity/Q2491525",
          "qnode_id": "Q2491525"
        }
      ]
    ],
    [
      [
        {
          "start": 0,
          "end": 17,
          "url": "http://www.wikidata.org/entity/Q26363401",
          "qnode_id": "Q26363401"
        }
      ],
      [
        {
          "start": 0,
          "end": 24,
          "url": "http://www.wikidata.org/entity/Q15700834",
          "qnode_id": "Q15700834"
        }
      ],
      [
        {
          "start": 0,
          "end": 17,
          "url": "http://www.wikidata.org/entity/Q2338783",
          "qnode_id": "Q2338783"
        }
      ]
    ],
    [
      [
        {
          "start": 0,
          "end": 22,
          "url": "http://www.wikidata.org/entity/Q26469433",
          "qnode_id": "Q26469433"
        }
      ],
      [
        {
          "start": 0,
          "end": 24,
          "url": "http://www.wikidata.org/entity/Q15700834",
          "qnode_id": "Q15700834"
        }
      ],
      [
        {
          "start": 0,
          "end": 16,
          "url": "http://www.wikidata.org/entity/Q2329378",
          "qnode_id": "Q2329378"
        }
      ]
    ]
  ]
}